minds_cli-0.1.1.dist-info/METADATA
minds_cli-0.1.1.dist-info/RECORD
minds_cli-0.1.1.dist-info/WHEEL
minds_cli-0.1.1.dist-info/entry_points.txt
minds_cli-0.1.1.dist-info/top_level.txt
mindscli/__init__.py
mindscli/output.py
mindscli/utils.py
mindscli/cli/__init__.py
mindscli/cli/interact.py
mindscli/cli/main.py
mindscli/cli/newsfeed.py
mindscli/cli/notifications.py
mindscli/cli/post.py
mindscli/cli/profile.py
mindscli/cli/show.py
mindscli/cli/user.py
