Metadata-Version: 2.1
Name: minds-cli
Version: 0.1.1
Summary: cli interface for minds-api
Home-page: https://gitlab.com/granitosaurus/minds-cli
Author: Bernardas Ališauskas
Author-email: bernard@hyperio.tech
License: GNU General Public License v3
Keywords: minds.com,cli,minds
Platform: UNKNOWN
Classifier: Development Status :: 2 - Pre-Alpha
Classifier: Intended Audience :: Developers
Classifier: License :: OSI Approved :: GNU General Public License v3 (GPLv3)
Classifier: Natural Language :: English
Classifier: Programming Language :: Python :: 3.6
Requires-Dist: Click (>=6.0)
Requires-Dist: minds
Requires-Dist: markdown
